sunblocker/__init__.py
sunblocker/sunblocker.py
sunblocker-1.0.1.dist-info/LICENSE
sunblocker-1.0.1.dist-info/METADATA
sunblocker-1.0.1.dist-info/WHEEL
sunblocker-1.0.1.dist-info/top_level.txt
sunblocker-1.0.1.dist-info/RECORD
