Metadata-Version: 2.1
Name: sunblocker
Version: 1.0.1
Summary: A (python pyrap) method to remove solar-like RFI from interferometric data
Home-page: https://github.com/gigjozsa/sunblocker
Author: Gyula I. G. Jozsa, Sphesihle Makhathini, Paolo Serra, Kshitij Thorath, Ben Hugo
Author-email: jozsa@ska.ac.za
License: GNU GPL v2
Platform: UNKNOWN
Classifier: Development Status :: 3 - Alpha
Classifier: Intended Audience :: Developers
Classifier: Operating System :: OS Independent
Classifier: Programming Language :: Python :: 2
Classifier: Topic :: Software Development :: Libraries :: Python Modules
Classifier: Topic :: Scientific/Engineering :: Astronomy
Requires-Python: >=2.6
Requires-Dist: numpy
Requires-Dist: python-casacore
Requires-Dist: matplotlib
Requires-Dist: scipy
Requires-Dist: astropy
Requires-Dist: ephem
